mypdns/__init__.py
mypdns-1.0.5.dist-info/LICENSE
mypdns-1.0.5.dist-info/METADATA
mypdns-1.0.5.dist-info/WHEEL
mypdns-1.0.5.dist-info/top_level.txt
mypdns-1.0.5.dist-info/RECORD
